oops_datedir_repo/__init__.py
oops_datedir_repo/anybson.py
oops_datedir_repo/bsondump.py
oops_datedir_repo/prune.py
oops_datedir_repo/repository.py
oops_datedir_repo/serializer.py
oops_datedir_repo/serializer_bson.py
oops_datedir_repo/serializer_rfc822.py
oops_datedir_repo-0.1.0.dist-info/licenses/LICENSE
oops_datedir_repo-0.1.0.dist-info/METADATA
oops_datedir_repo-0.1.0.dist-info/WHEEL
oops_datedir_repo-0.1.0.dist-info/entry_points.txt
oops_datedir_repo-0.1.0.dist-info/top_level.txt
oops_datedir_repo-0.1.0.dist-info/RECORD
