Metadata-Version: 2.4
Name: oops_datedir_repo
Version: 0.1.0
Summary: OOPS disk serialisation and repository management.
Home-page: https://launchpad.net/python-oops-datedir-repo
Author-email: launchpad-dev@lists.launchpad.net
Maintainer: Launchpad Developers
Maintainer-email: launchpad-dev@lists.launchpad.net
Classifier: Development Status :: 2 - Pre-Alpha
Classifier: Intended Audience :: Developers
Classifier: License :: OSI Approved :: GNU Library or Lesser General Public License (LGPL)
Classifier: Operating System :: OS Independent
Classifier: Programming Language :: Python
Classifier: Programming Language :: Python :: 3
Classifier: Programming Language :: Python :: 3.8
Requires-Python: >=3.8
License-File: LICENSE
Requires-Dist: bson
Requires-Dist: iso8601
Requires-Dist: launchpadlib
Requires-Dist: oops>=0.1.0
Requires-Dist: pytz
Provides-Extra: test
Requires-Dist: fixtures; extra == "test"
Requires-Dist: testtools; extra == "test"
Dynamic: author-email
Dynamic: classifier
Dynamic: description
Dynamic: description-content-type
Dynamic: home-page
Dynamic: license-file
Dynamic: maintainer
Dynamic: maintainer-email
Dynamic: provides-extra
Dynamic: requires-dist
Dynamic: requires-python
Dynamic: summary
